jira_tool_edit/__init__.py
jira_tool_edit/__main__.py
edit_jira-0.0.9.dist-info/METADATA
edit_jira-0.0.9.dist-info/WHEEL
edit_jira-0.0.9.dist-info/entry_points.txt
edit_jira-0.0.9.dist-info/top_level.txt
edit_jira-0.0.9.dist-info/RECORD
