Metadata-Version: 2.1
Name: edit-jira
Version: 0.0.9
Summary: edit markdown file to jira issue
Home-page: https://github.com/LogosFu/jira_tool
Author: LogosFu
Author-email: logosfu@gmail.com
License: GNU General Public License v3.0
Platform: UNKNOWN
Requires-Python: >=3.6
Requires-Dist: setuptools (~=57.1.0)
Requires-Dist: mistletoe (~=0.7.2)
Requires-Dist: requests (~=2.25.1)
